dash_building_blocks/__init__.py
dash_building_blocks/base.py
dash_building_blocks/core.py
dash_building_blocks/error.py
dash_building_blocks/util.py
dash_building_blocks-0.1.2.dist-info/METADATA
dash_building_blocks-0.1.2.dist-info/RECORD
dash_building_blocks-0.1.2.dist-info/WHEEL
dash_building_blocks-0.1.2.dist-info/top_level.txt
