Metadata-Version: 2.1
Name: dash-building-blocks
Version: 0.1.2
Summary: Lightweight Auxiliary Framework for Writing Object-Oriented Dash Code.
Home-page: http://github.com/AlgorithmHub/dash_buildin_blocks
Maintainer: Marco de Lannoy Kobayashi
Maintainer-email: mdlkdev@gmail.com
License: MIT
Keywords: dash object-oriented-programming
Platform: UNKNOWN
Classifier: Development Status :: 3 - Alpha
Classifier: Intended Audience :: Science/Research
Classifier: Intended Audience :: Developers
Classifier: License :: OSI Approved
Classifier: Programming Language :: Python
Classifier: Topic :: Software Development
Classifier: Topic :: Scientific/Engineering
Classifier: Operating System :: Microsoft :: Windows
Classifier: Operating System :: POSIX
Classifier: Operating System :: Unix
Classifier: Operating System :: MacOS
Classifier: Programming Language :: Python :: 3 :: Only
Requires-Dist: dash (>=0.22.0)
Requires-Dist: dash-html-components
Requires-Dist: dash-core-components
